microdata_validator/__init__.py
microdata_validator/adapter/local_storage.py
microdata_validator/components/temporal_attributes.py
microdata_validator/components/unit_id_types.py
microdata_validator/components/unit_type_variables/BK_HELSESTASJONSKONSULTASJON.json
microdata_validator/components/unit_type_variables/FAMILIE.json
microdata_validator/components/unit_type_variables/FORETAK.json
microdata_validator/components/unit_type_variables/HUSHOLDNING.json
microdata_validator/components/unit_type_variables/JOBB.json
microdata_validator/components/unit_type_variables/KJORETOY.json
microdata_validator/components/unit_type_variables/KOMMUNE.json
microdata_validator/components/unit_type_variables/KURS.json
microdata_validator/components/unit_type_variables/PERSON.json
microdata_validator/components/unit_type_variables/VIRKSOMHET.json
microdata_validator/components/unit_type_variables/__init__.py
microdata_validator/exceptions/__init__.py
microdata_validator/model/__init__.py
microdata_validator/model/metadata.py
microdata_validator/steps/dataset_reader.py
microdata_validator/steps/dataset_validator.py
microdata_validator/steps/metadata_inliner.py
microdata_validator/steps/metadata_reader.py
microdata_validator-7.3.5.dist-info/LICENSE.md
microdata_validator-7.3.5.dist-info/METADATA
microdata_validator-7.3.5.dist-info/WHEEL
microdata_validator-7.3.5.dist-info/RECORD
