Metadata-Version: 2.1
Name: microdata-validator
Version: 7.3.5
Summary: Python package for validating datasets in the microdata platform
Home-page: https://github.com/statisticsnorway/microdata-validator
License: Apache-2.0
Author: microdata-developers
Requires-Python: >=3.7.2,<4.0
Classifier: License :: OSI Approved :: Apache Software License
Classifier: Programming Language :: Python :: 3
Classifier: Programming Language :: Python :: 3.8
Classifier: Programming Language :: Python :: 3.9
Classifier: Programming Language :: Python :: 3.10
Classifier: Programming Language :: Python :: 3.11
Requires-Dist: pydantic (>=1.10.4,<2.0.0)
Project-URL: Repository, https://github.com/statisticsnorway/microdata-validator
